asaa/__init__.py
asaa/assistant.py
asaa/cli.py
asaa/core.py
asaa/questions.yaml
asaa-0.1.2.dist-info/LICENSE
asaa-0.1.2.dist-info/METADATA
asaa-0.1.2.dist-info/WHEEL
asaa-0.1.2.dist-info/entry_points.txt
asaa-0.1.2.dist-info/top_level.txt
asaa-0.1.2.dist-info/RECORD
