Metadata-Version: 2.1
Name: asaa
Version: 0.1.2
Summary: The Application Security Assessment Assistant
License: MIT License
Project-URL: Homepage, https://github.com/andycaine/asaa
Project-URL: Documentation, https://github.com/andycaine/asaa?tab=readme-ov-file#asaa
Project-URL: Repository, https://github.com/andycaine/asaa.git
Keywords: security,AI,assistant
License-File: LICENSE
Requires-Dist: click
Requires-Dist: openai
Requires-Dist: pyyaml
